kgpt.py
kgpt-0.2.dist-info/METADATA
kgpt-0.2.dist-info/WHEEL
kgpt-0.2.dist-info/entry_points.txt
kgpt-0.2.dist-info/top_level.txt
kgpt-0.2.dist-info/RECORD
