Metadata-Version: 2.1
Name: kgpt
Version: 0.2
Summary: Tiny tool to use AI to generate code
Home-page: https://github.com/kvfrans/kgpt
Author: Kevin Frans
Author-email: kevinfrans2@gmail.com
License: MIT
Requires-Dist: click
